omero_vitessce/__init__.py
omero_vitessce/apps.py
omero_vitessce/forms.py
omero_vitessce/omero_vitessce_settings.py
omero_vitessce/urls.py
omero_vitessce/utils.py
omero_vitessce/views.py
omero_vitessce/static/VITESSCE_LICENSE
omero_vitessce/static/css/main.136fc852.css
omero_vitessce/static/css/main.136fc852.css.map
omero_vitessce/static/js/113.26f8c3d6.chunk.js
omero_vitessce/static/js/113.26f8c3d6.chunk.js.map
omero_vitessce/static/js/132.26347ec2.chunk.js
omero_vitessce/static/js/132.26347ec2.chunk.js.LICENSE.txt
omero_vitessce/static/js/132.26347ec2.chunk.js.map
omero_vitessce/static/js/149.f2ecfb60.chunk.js
omero_vitessce/static/js/149.f2ecfb60.chunk.js.map
omero_vitessce/static/js/160.2ed7b02b.chunk.js
omero_vitessce/static/js/160.2ed7b02b.chunk.js.LICENSE.txt
omero_vitessce/static/js/160.2ed7b02b.chunk.js.map
omero_vitessce/static/js/242.727ddc77.chunk.js
omero_vitessce/static/js/242.727ddc77.chunk.js.map
omero_vitessce/static/js/330.af49bc08.chunk.js
omero_vitessce/static/js/330.af49bc08.chunk.js.map
omero_vitessce/static/js/390.c898606b.chunk.js
omero_vitessce/static/js/390.c898606b.chunk.js.map
omero_vitessce/static/js/420.f982a71d.chunk.js
omero_vitessce/static/js/420.f982a71d.chunk.js.LICENSE.txt
omero_vitessce/static/js/420.f982a71d.chunk.js.map
omero_vitessce/static/js/495.99cef5f4.chunk.js
omero_vitessce/static/js/495.99cef5f4.chunk.js.map
omero_vitessce/static/js/497.e6b4aaa6.chunk.js
omero_vitessce/static/js/497.e6b4aaa6.chunk.js.map
omero_vitessce/static/js/527.fc0b1526.chunk.js
omero_vitessce/static/js/527.fc0b1526.chunk.js.map
omero_vitessce/static/js/536.c1fc53cc.chunk.js
omero_vitessce/static/js/536.c1fc53cc.chunk.js.map
omero_vitessce/static/js/568.47b3a6d1.chunk.js
omero_vitessce/static/js/568.47b3a6d1.chunk.js.LICENSE.txt
omero_vitessce/static/js/568.47b3a6d1.chunk.js.map
omero_vitessce/static/js/690.8876f324.chunk.js
omero_vitessce/static/js/690.8876f324.chunk.js.LICENSE.txt
omero_vitessce/static/js/690.8876f324.chunk.js.map
omero_vitessce-1.2.2.dist-info/LICENSE
omero_vitessce-1.2.2.dist-info/METADATA
omero_vitessce-1.2.2.dist-info/WHEEL
omero_vitessce-1.2.2.dist-info/top_level.txt
omero_vitessce-1.2.2.dist-info/RECORD
