Metadata-Version: 2.1
Name: omero-vitessce
Version: 1.2.2
Summary: OMERO Vitessce multimodal data viewer plugin for OMERO.web
Home-page: https://github.com/MicheleBortol/omero-vitessce
Author: Michele Bortolomeazzi
Author-email: michele.bortolomeazzi@dfkf.de
License: AGPLv3
Keywords: OMERO.web,OMERO,Vitessce,viewer
Requires-Python: >=3.9
License-File: LICENSE
Requires-Dist: vitessce==3.3.0
Requires-Dist: shapely==2.0.6
